LICENSE
MANIFEST.in
README.md
README.rst
setup.py
maro_auth/__init__.py
maro_auth/admin.py
maro_auth/apps.py
maro_auth/email_helpers.py
maro_auth/forms.py
maro_auth/models.py
maro_auth/settings.py
maro_auth/tests.py
maro_auth/urls.py
maro_auth/views.py
maro_auth.egg-info/PKG-INFO
maro_auth.egg-info/SOURCES.txt
maro_auth.egg-info/dependency_links.txt
maro_auth.egg-info/top_level.txt
maro_auth/migrations/0001_initial.py
maro_auth/migrations/__init__.py
maro_auth/templates/maro_auth/base.html
maro_auth/templates/maro_auth/login.html
maro_auth/templates/maro_auth/reset_password.html
maro_auth/templates/maro_auth/reset_password_complete.html
maro_auth/templates/maro_auth/reset_password_confirm.html
maro_auth/templates/maro_auth/reset_password_done.html
maro_auth/templates/maro_auth/set_password.html
maro_auth/templates/maro_auth/signup.html
maro_auth/templates/maro_auth/email/change_email.html
maro_auth/templates/maro_auth/email/change_email.txt
maro_auth/templates/maro_auth/email/reset_password.html
maro_auth/templates/maro_auth/email/reset_password.txt
maro_auth/templates/maro_auth/email/welcome_email.html
maro_auth/templates/maro_auth/email/welcome_email.txt